[
	{
		"selecao": "Bélgica",
		"bandeira": "belgica",
		"grupo": "F",
		"pontos": 4,
		"jogos": 3,
		"vitorias": 1,
		"empates": 1,
		"derrotas": 1,
		"gols_pro": 1,
		"gols_contra": 2,
		"saldo_de_gols": -1,
		"posicao": 3,
		"amarelos": 5,
		"vermelhos": 0
	},
	{
		"selecao": "Canadá",
		"bandeira": "canada",
		"grupo": "F",
		"pontos": 0,
		"jogos": 3,
		"vitorias": 0,
		"empates": 0,
		"derrotas": 3,
		"gols_pro": 2,
		"gols_contra": 7,
		"saldo_de_gols": -5,
		"posicao": 4,
		"amarelos": 8,
		"vermelhos": 0
	},
	{
		"selecao": "Marrocos",
		"bandeira": "marrocos",
		"grupo": "F",
		"pontos": 7,
		"jogos": 3,
		"vitorias": 2,
		"empates": 1,
		"derrotas": 0,
		"gols_pro": 4,
		"gols_contra": 1,
		"saldo_de_gols": 3,
		"posicao": 1,
		"amarelos": 2,
		"vermelhos": 0
	},
	{
		"selecao": "Croácia",
		"bandeira": "croacia",
		"grupo": "F",
		"pontos": 5,
		"jogos": 3,
		"vitorias": 1,
		"empates": 2,
		"derrotas": 0,
		"gols_pro": 4,
		"gols_contra": 1,
		"saldo_de_gols": 3,
		"posicao": 2,
		"amarelos": 2,
		"vermelhos": 0
	}
]